{
    "artist_id": "2GOgGMMJooNV8Yk2PjvzAa",
    "artist_name": "v8",
    "features_summary": [
        [
            0.175,
            0.278,
            0.304,
            0.345,
            0.487,
            0.309,
            0.062,
            26.0
        ],
        [
            0.823,
            0.918,
            0.947,
            0.961,
            0.982,
            0.936,
            0.039,
            26.0
        ],
        [
            0.097,
            0.359,
            0.398,
            0.454,
            0.524,
            0.385,
            0.105,
            26.0
        ],
        [
            0.066,
            0.099,
            0.12,
            0.177,
            0.319,
            0.141,
            0.064,
            26.0
        ],
        [
            0.0,
            0.0,
            0.002,
            0.006,
            0.127,
            0.01,
            0.026,
            26.0
        ],
        [
            0.0,
            0.0,
            0.0,
            0.0,
            0.231,
            0.013,
            0.046,
            26.0
        ],
        [
            0.038,
            0.113,
            0.192,
            0.312,
            0.688,
            0.242,
            0.172,
            26.0
        ]
    ],
    "measures_summary": [
        [
            71.121,
            101.248,
            130.108,
            140.282,
            166.598,
            123.001,
            25.235,
            26.0
        ],
        [
            -6.873,
            -5.718,
            -5.219,
            -4.623,
            -2.681,
            -5.177,
            0.902,
            26.0
        ],
        [
            100040.0,
            158629.75,
            204599.5,
            233239.75,
            371120.0,
            205767.308,
            60815.601,
            26.0
        ]
    ],
    "key_counts": [
        [
            0.0,
            0.0,
            0.0,
            1.0,
            1.0,
            5.0,
            4.0,
            0.0,
            0.0,
            0.0,
            0.0,
            0.0
        ],
        [
            1.0,
            3.0,
            3.0,
            4.0,
            1.0,
            2.0,
            1.0,
            0.0,
            0.0,
            0.0,
            0.0,
            0.0
        ]
    ],
    "albums": [
        {
            "album_id": "0zHdtlc987CwJR3Pr5TV5z",
            "album_name": "Un Paso Mas en la Batalla",
            "features_summary": [
                [
                    0.201,
                    0.242,
                    0.272,
                    0.291,
                    0.344,
                    0.27,
                    0.044,
                    8.0
                ],
                [
                    0.885,
                    0.908,
                    0.925,
                    0.951,
                    0.982,
                    0.928,
                    0.034,
                    8.0
                ],
                [
                    0.283,
                    0.405,
                    0.43,
                    0.493,
                    0.524,
                    0.434,
                    0.078,
                    8.0
                ],
                [
                    0.066,
                    0.084,
                    0.101,
                    0.14,
                    0.193,
                    0.115,
                    0.045,
                    8.0
                ],
                [
                    0.0,
                    0.002,
                    0.004,
                    0.006,
                    0.052,
                    0.009,
                    0.017,
                    8.0
                ],
                [
                    0.0,
                    0.0,
                    0.0,
                    0.0,
                    0.047,
                    0.006,
                    0.017,
                    8.0
                ],
                [
                    0.115,
                    0.309,
                    0.33,
                    0.404,
                    0.688,
                    0.371,
                    0.171,
                    8.0
                ]
            ],
            "measures_summary": [
                [
                    76.343,
                    95.158,
                    127.324,
                    131.979,
                    166.598,
                    118.762,
                    29.059,
                    8.0
                ],
                [
                    -6.548,
                    -5.572,
                    -5.282,
                    -4.782,
                    -4.371,
                    -5.268,
                    0.686,
                    8.0
                ],
                [
                    143306.0,
                    175780.0,
                    219653.0,
                    240373.0,
                    316413.0,
                    218011.375,
                    55391.531,
                    8.0
                ]
            ],
            "key_counts": [
                [
                    0.0,
                    0.0,
                    0.0,
                    0.0,
                    1.0,
                    1.0,
                    2.0,
                    0.0,
                    0.0,
                    0.0,
                    0.0,
                    0.0
                ],
                [
                    1.0,
                    1.0,
                    0.0,
                    1.0,
                    0.0,
                    0.0,
                    1.0,
                    0.0,
                    0.0,
                    0.0,
                    0.0,
                    0.0
                ]
            ],
            "tracks": [
                {
                    "track_id": "2zumIZU09Iz2eGRJ5UXHms",
                    "track_name": "Deseando Destruir y Matar",
                    "x": -1.53,
                    "y": 0.64,
                    "features": [
                        0.288,
                        0.982,
                        0.408,
                        0.103,
                        0.00599,
                        0.000318,
                        0.688
                    ],
                    "measures": [
                        90.765,
                        -4.81,
                        316413
                    ],
                    "key": 2,
                    "mode": 1
                },
                {
                    "track_id": "2eYIlRr6RkpU85a9ncU4bK",
                    "track_name": "Servios del Mal",
                    "x": -1.93,
                    "y": 0.79,
                    "features": [
                        0.3,
                        0.887,
                        0.487,
                        0.0863,
                        0.00518,
                        0.000336,
                        0.312
                    ],
                    "measures": [
                        124.23,
                        -6.548,
                        206106
                    ],
                    "key": 9,
                    "mode": 0
                },
                {
                    "track_id": "1ytzecQIGpLBfZpwXMCX3m",
                    "track_name": "La Mano Maldita",
                    "x": 3.02,
                    "y": -0.41,
                    "features": [
                        0.244,
                        0.915,
                        0.513,
                        0.0655,
                        0.00668,
                        0.0,
                        0.362
                    ],
                    "measures": [
                        131.398,
                        -4.699,
                        143306
                    ],
                    "key": 11,
                    "mode": 0
                },
                {
                    "track_id": "5h6i3AEIuCowRyypsQx2Gq",
                    "track_name": "Cautivos del Sistema",
                    "x": 2.59,
                    "y": -3.67,
                    "features": [
                        0.235,
                        0.954,
                        0.524,
                        0.166,
                        0.00299,
                        3.59e-06,
                        0.115
                    ],
                    "measures": [
                        96.622,
                        -5.582,
                        233200
                    ],
                    "key": 11,
                    "mode": 1
                },
                {
                    "track_id": "1ePOTmisnZBWoBEHJ5v31E",
                    "track_name": "Lanzado al Mundo Hoy",
                    "x": 4.03,
                    "y": 2.8,
                    "features": [
                        0.277,
                        0.931,
                        0.283,
                        0.0775,
                        0.0523,
                        0.047,
                        0.31
                    ],
                    "measures": [
                        76.343,
                        -4.371,
                        233253
                    ],
                    "key": 5,
                    "mode": 1
                },
                {
                    "track_id": "402W9iALZu6LtOC6kc8hq4",
                    "track_name": "Ideando la Fuga",
                    "x": 0.31,
                    "y": 0.53,
                    "features": [
                        0.344,
                        0.885,
                        0.434,
                        0.131,
                        1.44e-05,
                        0.0,
                        0.305
                    ],
                    "measures": [
                        130.417,
                        -5.568,
                        176520
                    ],
                    "key": 0,
                    "mode": 1
                },
                {
                    "track_id": "26qopSV1KsnVIl2FwjAcJS",
                    "track_name": "Camino al Sepulcro",
                    "x": 3.13,
                    "y": 2.29,
                    "features": [
                        0.201,
                        0.918,
                        0.397,
                        0.0987,
                        0.00221,
                        2.42e-06,
                        0.531
                    ],
                    "measures": [
                        166.598,
                        -5.539,
                        261733
                    ],
                    "key": 11,
                    "mode": 0
                },
                {
                    "track_id": "3Vm3YWPdxpYStMg2OOFrtU",
                    "track_name": "Momento de Lucha",
                    "x": 4.96,
                    "y": 1.13,
                    "features": [
                        0.268,
                        0.95,
                        0.425,
                        0.193,
                        0.000189,
                        0.0,
                        0.348
                    ],
                    "measures": [
                        133.724,
                        -5.026,
                        173560
                    ],
                    "key": 4,
                    "mode": 0
                }
            ]
        },
        {
            "album_id": "1t0PS8ygv5ojjmNl1JmVPf",
            "album_name": "El Fin de los Inicuos",
            "features_summary": [
                [
                    0.277,
                    0.288,
                    0.305,
                    0.345,
                    0.373,
                    0.314,
                    0.035,
                    9.0
                ],
                [
                    0.823,
                    0.918,
                    0.927,
                    0.957,
                    0.977,
                    0.923,
                    0.05,
                    9.0
                ],
                [
                    0.097,
                    0.356,
                    0.38,
                    0.45,
                    0.519,
                    0.365,
                    0.129,
                    9.0
                ],
                [
                    0.083,
                    0.103,
                    0.11,
                    0.21,
                    0.319,
                    0.157,
                    0.079,
                    9.0
                ],
                [
                    0.0,
                    0.0,
                    0.0,
                    0.001,
                    0.014,
                    0.002,
                    0.004,
                    9.0
                ],
                [
                    null,
                    null,
                    null,
                    null,
                    null,
                    null,
                    null,
                    null
                ],
                [
                    0.082,
                    0.096,
                    0.161,
                    0.202,
                    0.675,
                    0.204,
                    0.185,
                    9.0
                ]
            ],
            "measures_summary": [
                [
                    115.128,
                    123.127,
                    129.799,
                    139.882,
                    153.475,
                    131.008,
                    12.073,
                    9.0
                ],
                [
                    -6.873,
                    -5.885,
                    -5.739,
                    -5.344,
                    -5.123,
                    -5.793,
                    0.56,
                    9.0
                ],
                [
                    149253.0,
                    206786.0,
                    220466.0,
                    237106.0,
                    298013.0,
                    221003.889,
                    39988.151,
                    9.0
                ]
            ],
            "key_counts": [
                [
                    0.0,
                    0.0,
                    0.0,
                    0.0,
                    0.0,
                    4.0,
                    1.0,
                    0.0,
                    0.0,
                    0.0,
                    0.0,
                    0.0
                ],
                [
                    0.0,
                    0.0,
                    3.0,
                    1.0,
                    0.0,
                    0.0,
                    0.0,
                    0.0,
                    0.0,
                    0.0,
                    0.0,
                    0.0
                ]
            ],
            "tracks": [
                {
                    "track_id": "2pXJVQCY7JnTLIPndpJ0yH",
                    "track_name": "La Gran Ramera",
                    "x": -1.85,
                    "y": 2.61,
                    "features": [
                        0.295,
                        0.918,
                        0.45,
                        0.104,
                        1.95e-05,
                        0.000276,
                        0.245
                    ],
                    "measures": [
                        140.415,
                        -5.813,
                        193653
                    ],
                    "key": 11,
                    "mode": 0
                },
                {
                    "track_id": "1vceYAVuScSsCQwvbkWT8j",
                    "track_name": "Ciega Ambicion",
                    "x": -1.75,
                    "y": 1.32,
                    "features": [
                        0.28,
                        0.963,
                        0.428,
                        0.0988,
                        0.000112,
                        1.49e-05,
                        0.202
                    ],
                    "measures": [
                        115.128,
                        -5.123,
                        216986
                    ],
                    "key": 4,
                    "mode": 0
                },
                {
                    "track_id": "6KMbJSTSecyfoD5NgXiQvh",
                    "track_name": "No Enloquecere",
                    "x": -1.89,
                    "y": 1.01,
                    "features": [
                        0.352,
                        0.957,
                        0.459,
                        0.11,
                        8.09e-05,
                        0.000165,
                        0.116
                    ],
                    "measures": [
                        129.799,
                        -5.654,
                        220466
                    ],
                    "key": 4,
                    "mode": 0
                },
                {
                    "track_id": "4zymqtwxceeOlUebIemgdU",
                    "track_name": "El Vivo Sustento del Inquisidor",
                    "x": -1.17,
                    "y": 0.47,
                    "features": [
                        0.277,
                        0.927,
                        0.233,
                        0.0831,
                        0.00138,
                        0.000151,
                        0.0959
                    ],
                    "measures": [
                        139.882,
                        -6.426,
                        242906
                    ],
                    "key": 4,
                    "mode": 0
                },
                {
                    "track_id": "5dQ9nup0Lsc3Z5nQKK9PYd",
                    "track_name": "Antes Que los Viejos Reyes",
                    "x": -1.09,
                    "y": 2.24,
                    "features": [
                        0.345,
                        0.866,
                        0.367,
                        0.103,
                        0.000279,
                        6.48e-06,
                        0.0824
                    ],
                    "measures": [
                        123.127,
                        -5.885,
                        223866
                    ],
                    "key": 7,
                    "mode": 1
                },
                {
                    "track_id": "21QlQNcw94t8W836NjTwRX",
                    "track_name": "Salmo N\u00ba58",
                    "x": -1.44,
                    "y": 0.69,
                    "features": [
                        0.288,
                        0.823,
                        0.0972,
                        0.223,
                        0.0136,
                        0.0,
                        0.0906
                    ],
                    "measures": [
                        153.475,
                        -6.873,
                        298013
                    ],
                    "key": 7,
                    "mode": 1
                },
                {
                    "track_id": "6UXRmSINHZ0mEL2bknDKdN",
                    "track_name": "El Fin de los Inicuos",
                    "x": -1.59,
                    "y": 0.97,
                    "features": [
                        0.305,
                        0.977,
                        0.356,
                        0.163,
                        6.43e-05,
                        0.00313,
                        0.171
                    ],
                    "measures": [
                        133.379,
                        -5.279,
                        149253
                    ],
                    "key": 7,
                    "mode": 1
                },
                {
                    "track_id": "2emTXTG3FsnXgmD4GNzIHS",
                    "track_name": "Tragico Siglo",
                    "x": -1.68,
                    "y": 1.09,
                    "features": [
                        0.373,
                        0.954,
                        0.519,
                        0.21,
                        0.00315,
                        1.38e-06,
                        0.161
                    ],
                    "measures": [
                        123.94,
                        -5.344,
                        206786
                    ],
                    "key": 4,
                    "mode": 0
                },
                {
                    "track_id": "7GTXT02XoUPev1xdsN0MgX",
                    "track_name": "Reina Ciega",
                    "x": -1.61,
                    "y": 1.42,
                    "features": [
                        0.308,
                        0.92,
                        0.38,
                        0.319,
                        0.00134,
                        0.0,
                        0.675
                    ],
                    "measures": [
                        119.931,
                        -5.739,
                        237106
                    ],
                    "key": 2,
                    "mode": 1
                }
            ]
        },
        {
            "album_id": "4KDgm8j9XKonRf5S3aQfQE",
            "album_name": "Luchando por el Metal",
            "features_summary": [
                [
                    0.175,
                    0.326,
                    0.338,
                    0.365,
                    0.487,
                    0.34,
                    0.081,
                    9.0
                ],
                [
                    0.928,
                    0.944,
                    0.953,
                    0.974,
                    0.981,
                    0.958,
                    0.019,
                    9.0
                ],
                [
                    0.219,
                    0.286,
                    0.387,
                    0.399,
                    0.488,
                    0.361,
                    0.094,
                    9.0
                ],
                [
                    0.07,
                    0.115,
                    0.129,
                    0.181,
                    0.252,
                    0.149,
                    0.063,
                    9.0
                ],
                [
                    0.0,
                    0.001,
                    0.003,
                    0.012,
                    0.127,
                    0.02,
                    0.041,
                    9.0
                ],
                [
                    0.0,
                    0.0,
                    0.0,
                    0.007,
                    0.231,
                    0.031,
                    0.076,
                    9.0
                ],
                [
                    0.038,
                    0.108,
                    0.143,
                    0.195,
                    0.314,
                    0.164,
                    0.089,
                    9.0
                ]
            ],
            "measures_summary": [
                [
                    71.121,
                    92.541,
                    131.755,
                    145.063,
                    151.416,
                    118.761,
                    31.544,
                    9.0
                ],
                [
                    -6.031,
                    -4.677,
                    -4.511,
                    -4.462,
                    -2.681,
                    -4.482,
                    0.915,
                    9.0
                ],
                [
                    100040.0,
                    147013.0,
                    153653.0,
                    184546.0,
                    371120.0,
                    179647.111,
                    78073.973,
                    9.0
                ]
            ],
            "key_counts": [
                [
                    0.0,
                    0.0,
                    0.0,
                    1.0,
                    0.0,
                    0.0,
                    1.0,
                    0.0,
                    0.0,
                    0.0,
                    0.0,
                    0.0
                ],
                [
                    0.0,
                    2.0,
                    0.0,
                    2.0,
                    1.0,
                    2.0,
                    0.0,
                    0.0,
                    0.0,
                    0.0,
                    0.0,
                    0.0
                ]
            ],
            "tracks": [
                {
                    "track_id": "3uA2mxyUauUv8quA4w5jD6",
                    "track_name": "Destrucci\u00f3n",
                    "x": 3.89,
                    "y": 1.77,
                    "features": [
                        0.357,
                        0.974,
                        0.286,
                        0.234,
                        0.000924,
                        5.71e-05,
                        0.314
                    ],
                    "measures": [
                        145.063,
                        -3.743,
                        128426
                    ],
                    "key": 2,
                    "mode": 1
                },
                {
                    "track_id": "3nsxyFSYRNefygBeEvnfc6",
                    "track_name": "Parcas Sangrientas",
                    "x": 2.17,
                    "y": 0.19,
                    "features": [
                        0.487,
                        0.951,
                        0.399,
                        0.115,
                        0.000442,
                        0.231,
                        0.143
                    ],
                    "measures": [
                        94.294,
                        -6.031,
                        178000
                    ],
                    "key": 2,
                    "mode": 1
                },
                {
                    "track_id": "4azluUxfAo7cT4M77Wc4nM",
                    "track_name": "Si Puedes Vencer al Temor",
                    "x": 4.38,
                    "y": 1.74,
                    "features": [
                        0.175,
                        0.94,
                        0.395,
                        0.086,
                        0.00519,
                        0.0415,
                        0.108
                    ],
                    "measures": [
                        71.121,
                        -4.511,
                        371120
                    ],
                    "key": 0,
                    "mode": 1
                },
                {
                    "track_id": "3LuOboY25F2aRGF2yzsNol",
                    "track_name": "\u00c1ngel de las Tinieblas",
                    "x": 4.91,
                    "y": -0.54,
                    "features": [
                        0.304,
                        0.944,
                        0.488,
                        0.0695,
                        0.000702,
                        0.0,
                        0.0379
                    ],
                    "measures": [
                        88.939,
                        -4.605,
                        153653
                    ],
                    "key": 4,
                    "mode": 1
                },
                {
                    "track_id": "4T2kryjqmT3TRJhcni4OaK",
                    "track_name": "Tiempos Met\u00e1licos",
                    "x": 4.88,
                    "y": 2.31,
                    "features": [
                        0.338,
                        0.979,
                        0.237,
                        0.252,
                        0.0275,
                        0.000102,
                        0.1
                    ],
                    "measures": [
                        148.994,
                        -4.677,
                        150933
                    ],
                    "key": 0,
                    "mode": 1
                },
                {
                    "track_id": "5HvOWXV84hNU01ge2EnVhJ",
                    "track_name": "Muy Cansado Estoy",
                    "x": 2.38,
                    "y": -0.3,
                    "features": [
                        0.328,
                        0.928,
                        0.387,
                        0.181,
                        0.0122,
                        0.000283,
                        0.112
                    ],
                    "measures": [
                        144.725,
                        -4.462,
                        203093
                    ],
                    "key": 4,
                    "mode": 1
                },
                {
                    "track_id": "3JfieA8AhdSTGXHAAAr4Uy",
                    "track_name": "Brigadas Met\u00e1licas",
                    "x": 4.93,
                    "y": 0.74,
                    "features": [
                        0.326,
                        0.981,
                        0.219,
                        0.151,
                        0.127,
                        1.71e-06,
                        0.195
                    ],
                    "measures": [
                        131.755,
                        -2.681,
                        184546
                    ],
                    "key": 2,
                    "mode": 0
                },
                {
                    "track_id": "5Goh3OnlrAB8GM2AUTsrrh",
                    "track_name": "Torturador",
                    "x": 4.83,
                    "y": 2.11,
                    "features": [
                        0.377,
                        0.971,
                        0.385,
                        0.129,
                        0.00316,
                        0.000142,
                        0.189
                    ],
                    "measures": [
                        92.541,
                        -4.466,
                        147013
                    ],
                    "key": 9,
                    "mode": 1
                },
                {
                    "track_id": "68eYBVrkPO7arQWmf5FGKU",
                    "track_name": "Hiena de Metal",
                    "x": 4.73,
                    "y": 1.12,
                    "features": [
                        0.365,
                        0.953,
                        0.456,
                        0.124,
                        1.58e-05,
                        0.00656,
                        0.277
                    ],
                    "measures": [
                        151.416,
                        -5.159,
                        100040
                    ],
                    "key": 11,
                    "mode": 0
                }
            ]
        }
    ]
}